Metadata-Version: 2.1
Name: unique-characters-TurchinskiyD
Version: 0.0.1
Summary: The module counts how many unique characters are in the string or file it is processing.
Home-page: https://git.foxminded.com.ua/foxstudent101495/unique_characters
Author-email: turchinskiyd@gmail.com
License: MIT License, see LICENSE file
Platform: UNKNOWN
Classifier: Operating System :: OS Independent
Classifier: Intended Audience :: End Users/Desktop
Classifier: Intended Audience :: Developers
Classifier: Programming Language :: Python
Classifier: Programming Language :: Python :: Implementation :: PyPy
Classifier: Programming Language :: Python :: Implementation :: CPython
License-File: LICENSE
